{
 "count": 104,
 "proposal": [
  {
   "page": "dq_dinh_muc_dinh_muc_so_che",
   "title": "Định mức sơ chế",
   "dataSource": "ds_dinhmuc_govan",
   "fromForm": "frmDinhMucSoChe",
   "matchType": "title",
   "setFields": [
    "masp",
    "mact",
    "id",
    "stt",
    "chitiet",
    "nguyenlieu",
    "dayy_tc",
    "rong_tc",
    "dai_tc",
    "soluong_tc",
    "m3_tc",
    "dayy_sc",
    "rong_sc",
    "dai_sc",
    "soluong_sc",
    "m3_sc"
   ]
  },
  {
   "page": "dinh_muc_ngu_kim_e69c33",
   "title": "Định mức ngũ kim",
   "dataSource": "ds_dinhmuc_ngukim",
   "fromForm": "frm_add_dinhmuc_nk",
   "matchType": "title",
   "setFields": [
    "masp",
    "mavt",
    "stt",
    "chitiet",
    "quycach",
    "slchet",
    "slroi",
    "soluong",
    "dvt",
    "nhom",
    "bophan_sudung",
    "ghichu",
    "id"
   ]
  },
  {
   "page": "dq_kho_vat_tu_yeu_cau_chat_luong_add",
   "title": "Cập nhật yêu cầu chất lượng",
   "dataSource": "ds_m_op",
   "fromForm": "frmYeuCauChatLuongAdd",
   "matchType": "title",
   "setFields": [
    "c_op",
    "n_op",
    "yeucau_chatluong",
    "id"
   ]
  },
  {
   "page": "dq_kho_vat_tu_phieu_bu_hang_add",
   "title": "Phiếu bù hàng",
   "dataSource": "ds_dinhmuc_govan",
   "fromForm": "frmPhieuBuHangAdd",
   "matchType": "title",
   "setFields": [
    "nguyenlieu",
    "ghichu",
    "mact",
    "chitiet",
    "soluong_tc",
    "stt",
    "dayy_tc",
    "rong_tc",
    "dai_tc"
   ]
  },
  {
   "page": "dq_dinh_muc_add_dinhmuc_vt_ver2",
   "title": "Cập nhật định mức gỗ ván",
   "dataSource": "ds_dinhmuc_govan",
   "fromForm": "frm_add_dinhmuc_vt_ver2",
   "matchType": "title",
   "setFields": [
    "stt",
    "mact",
    "chitiet",
    "nguyenlieu",
    "dayy_tc",
    "rong_tc",
    "dai_tc",
    "soluong_tc",
    "m3_tc",
    "dayy_sc",
    "rong_sc",
    "dai_sc",
    "m3_sc",
    "ghichu",
    "id",
    "masp"
   ]
  },
  {
   "page": "dq_danh_muc_danh_sach_xuat_go_van",
   "title": "Danh sách phiếu xuất gỗ ván",
   "dataSource": "ds_phieuxuat",
   "fromForm": "frmDanhSachXuatGoVan",
   "matchType": "title",
   "setFields": [
    "id",
    "ngayxuat"
   ]
  },
  {
   "page": "dq_danh_muc_list_bom_editor",
   "title": "Danh sách sản phẩm",
   "dataSource": "ds_sanpham",
   "fromForm": "frmThongtinsanpham",
   "matchType": "title",
   "setFields": [
    "id",
    "masp",
    "tensp",
    "dai",
    "rong",
    "cao",
    "dvt"
   ]
  },
  {
   "page": "dq_dinh_muc_dinh_muc_don_hang",
   "title": "frmDinhMucDonHang",
   "dataSource": "ds_sanpham",
   "fromForm": "frmDinhMucDonHang",
   "matchType": "title",
   "setFields": [
    "hehang",
    "masp",
    "tensp",
    "mausac",
    "dvt"
   ]
  },
  {
   "page": "dq_dinh_muc_dinh_muc_go_van_so_che",
   "title": "frmDinhMucGoVanSoChe",
   "dataSource": "ds_dinhmuc_govan",
   "fromForm": "frmDinhMucGoVanSoChe",
   "matchType": "title",
   "setFields": [
    "masp",
    "stt",
    "mact",
    "chitiet",
    "nguyenlieu",
    "dayy_sc",
    "rong_sc",
    "dai_sc",
    "soluong_sc",
    "veneer_matchinh",
    "id",
    "veneer_matphu",
    "ghichu"
   ]
  },
  {
   "page": "dq_kho_vat_tu_warehouse_finish_good_input",
   "title": "Nhập thành phẩm",
   "dataSource": "ds_sanpham",
   "fromForm": "frmWarehouseFinishGoodInput",
   "matchType": "title",
   "setFields": [
    "masp_khachhang",
    "dvt",
    "id",
    "masp",
    "tensp",
    "hehang",
    "ghichu"
   ]
  },
  {
   "page": "dq_kho_vat_tu_warehouse_input_htr",
   "title": "Nhập kho hàng trắng",
   "dataSource": "ds_dinhmuc_govan",
   "fromForm": "frmWarehouseInput_HTR",
   "matchType": "title",
   "setFields": [
    "masp",
    "mact",
    "stt",
    "chitiet",
    "nguyenlieu",
    "dayy_tc",
    "rong_tc",
    "dai_tc",
    "soluong_tc",
    "ghichu"
   ]
  },
  {
   "page": "dq_dinh_muc_dinh_muc_chi_phi_san_pham",
   "title": "Định mức chi phí sản phẩm",
   "dataSource": "ds_sanpham",
   "fromForm": "frmDinhMucChiPhiSanPham",
   "matchType": "title",
   "setFields": [
    "masp",
    "nguyenlieu",
    "m3_tc",
    "tensp",
    "hehang",
    "dongia_son",
    "id"
   ]
  },
  {
   "page": "dq_kho_vat_tu_phieu_xuat_cont",
   "title": "Phiếu xuất cont",
   "dataSource": "ds_order_detail",
   "fromForm": "frmPhieuXuatCont",
   "matchType": "title",
   "setFields": [
    "order_number",
    "cust_po_number",
    "range",
    "id",
    "item_number",
    "description",
    "order_qty",
    "ship_qty",
    "cbm"
   ]
  },
  {
   "page": "dq_danh_muc_create_material_request_gva_ver2",
   "title": "Lệnh cấp phát gỗ ván",
   "dataSource": "ds_dondathang",
   "fromForm": "frmCreateMaterialRequest_GVA_ver2",
   "matchType": "title",
   "setFields": [
    "maddh",
    "nhom"
   ]
  },
  {
   "page": "dq_danh_muc_danh_muc_de_xuat2",
   "title": "frmDanhMucDeXuat2",
   "dataSource": "ds_dexuat_bangmau",
   "fromForm": "frmDanhMucDeXuat2",
   "matchType": "title",
   "setFields": [
    "id",
    "sophieu",
    "ngaydexuat",
    "mucdich",
    "nguoitao"
   ]
  },
  {
   "page": "dq_danh_muc_nhom_may",
   "title": "Nhóm máy",
   "dataSource": "ds_m_op",
   "fromForm": "frmNhomMay",
   "matchType": "title",
   "setFields": [
    "p_op",
    "c_op",
    "n_op",
    "id",
    "id_maymoc"
   ]
  },
  {
   "page": "dq_danh_muc_danh_muc_loi_add",
   "title": "Cập nhật danh mục lỗi",
   "dataSource": "ds_baocao_hangloi",
   "fromForm": "frmDanhMucLoiAdd",
   "matchType": "title",
   "setFields": [
    "tinhtrang",
    "nguyennhankhac",
    "id",
    "tacnhangayloi"
   ]
  },
  {
   "page": "dq_kho_vat_tu_tao_phieu_pallet",
   "title": "frmTaoPhieuPallet",
   "dataSource": "ds_pallet",
   "fromForm": "frmTaoPhieuPallet",
   "matchType": "title",
   "setFields": [
    "masp",
    "stt",
    "mact",
    "tenct",
    "nguyenlieu",
    "id",
    "dayy_tc",
    "rong_tc",
    "dai_tc",
    "soluong_tc",
    "soluong_donhang",
    "soluong_can",
    "ghichu",
    "card_qty",
    "iscreatecard"
   ]
  },
  {
   "page": "dq_don_hang_proforma_invoice_add_1",
   "title": "Danhh sách sản phẩm",
   "dataSource": "ds_order_detail",
   "fromForm": "frmProformaInvoiceAdd_1",
   "matchType": "title",
   "setFields": [
    "order_number",
    "cust_po_number",
    "item_number",
    "order_qty",
    "cbm",
    "price"
   ]
  },
  {
   "page": "dq_don_hang_order_number_add",
   "title": "Tạo đơn hàng",
   "dataSource": "ds_order_detail",
   "fromForm": "frmOrderNumberAdd2",
   "matchType": "title",
   "setFields": [
    "order_qty",
    "price",
    "currency",
    "cbm",
    "id",
    "range",
    "cust_item_number",
    "color",
    "material",
    "test_run_qty"
   ]
  },
  {
   "page": "dq_kho_vat_tu_nhap_hang_loi_add",
   "title": "hàng lỗi - hàng đổi trả",
   "dataSource": "ds_dinhmuc_govan",
   "fromForm": "frmNhapHangLoi",
   "matchType": "title",
   "setFields": [
    "id",
    "masp",
    "mact",
    "nguoisua",
    "ngaysua",
    "nguoitao",
    "ngaytao"
   ]
  },
  {
   "page": "dq_kho_vat_tu_theo_doi_nhap_xuat_chi_tiet",
   "title": "Chi tiết nhập - xuất: ",
   "dataSource": "ds_phieuxuat",
   "fromForm": "frmTheoDoiNhapXuat_ChiTiet",
   "matchType": "title",
   "setFields": [
    "maddh",
    "ghichu",
    "lenhcapphat",
    "nguoinhan",
    "ngaytao",
    "sopx"
   ]
  },
  {
   "page": "dq_kho_vat_tu_phieu_giao_thanh_pham",
   "title": "Phiếu giao thành phẩm",
   "dataSource": "ds_phieuxuat",
   "fromForm": "frmPhieuGiaoThanhPham",
   "matchType": "title",
   "setFields": [
    "ngaytao",
    "nguoitao",
    "id"
   ]
  },
  {
   "page": "dq_kho_vat_tu_ton_kho_go_van_chon_quy_cach",
   "title": "Chọn quy cách",
   "dataSource": "ds_dexuat_phoi_chitiet",
   "fromForm": "frmTonKhoGoVan_ChonQuyCach",
   "matchType": "title",
   "setFields": [
    "id",
    "sothanh_yc",
    "sokhoi_yc"
   ]
  },
  {
   "page": "dq_kho_vat_tu_nhap_hang_loi2",
   "title": "Nhập chi tiết lỗi",
   "dataSource": "ds_dinhmuc_govan",
   "fromForm": "frmNhapHangLoi2",
   "matchType": "title",
   "setFields": [
    "id",
    "mact",
    "stt",
    "chitiet",
    "nguyenlieu",
    "dayy_tc",
    "rong_tc",
    "dai_tc",
    "masp"
   ]
  },
  {
   "page": "dq_kho_vat_tu_phieu_de_nghi_thanh_toan",
   "title": "Danh sách phiếu đề nghị thanh toán",
   "dataSource": "de_nghi_thanh_toan_joined_019eb9",
   "fromForm": "frmPhieuDeNghiThanhToan",
   "matchType": "title",
   "setFields": [
    "id",
    "ngayphieu",
    "sophieu",
    "nguoidenghi",
    "bophan",
    "nguoitao",
    "ngaytao",
    "loaithanhtoan",
    "noidung",
    "dathanhtoan",
    "sotien",
    "thue",
    "phigiaohang",
    "thanhtien",
    "loaitien",
    "tygia",
    "nguoiduyet",
    "ngayduyet"
   ]
  },
  {
   "page": "dq_kho_vat_tu_nhap_hang_loi",
   "title": "Hàng lỗi - hàng đổi trả",
   "dataSource": "ds_baocao_hangloi",
   "fromForm": "frmNhapHangLoi",
   "matchType": "title",
   "setFields": [
    "id",
    "donhang",
    "ngaythang",
    "masp",
    "mact",
    "tenct",
    "dayy",
    "rong",
    "dai",
    "soluong",
    "soluong_xuly",
    "tinhtrang",
    "nguyennhan",
    "nguoiphutrach",
    "nguoisua",
    "ngaysua",
    "xuongphoi",
    "xuongdinhhinh",
    "xuonghoanthien",
    "huongxuly",
    "nguoitao",
    "ngaytao"
   ]
  },
  {
   "page": "dq_kho_vat_tu_nhap_hang_loi3",
   "title": "Báo cáo hàng lỗi",
   "dataSource": "ds_baocao_hangloi",
   "fromForm": "frmNhapHangLoi3",
   "matchType": "title",
   "setFields": [
    "ngaythang",
    "donhang",
    "masp",
    "mact",
    "tenct",
    "nguyenlieu",
    "dayy",
    "rong",
    "dai",
    "soluong",
    "tinhtrang",
    "loailoi",
    "tacnhangayloi",
    "nguyennhanloi",
    "nguyennhankhac",
    "huongxuly",
    "id",
    "iscreatecard",
    "daxuly",
    "card_no",
    "nguoiduyet",
    "bophantra",
    "bophanlamloi",
    "congdoanhientai",
    "nguoiphutrach"
   ]
  },
  {
   "page": "dq_don_hang_proforma_invoice",
   "title": "Proforma Invoice",
   "dataSource": "ds_order",
   "fromForm": "frmProformaInvoice",
   "matchType": "title",
   "setFields": [
    "id",
    "cust_po_number",
    "customer"
   ]
  },
  {
   "page": "dq_don_hang_banhanggo_danh_sach_de_xuat_phoi",
   "title": "Danh sách đề xuất phôi",
   "dataSource": "ds_dexuat_phoi_chitiet",
   "fromForm": "frm_banhanggo_DanhSachDeXuatPhoi",
   "matchType": "title",
   "setFields": [
    "dexuat_id",
    "id",
    "isfinish",
    "ngaygiaophoi",
    "nguongoc_giao",
    "chatluong_giao",
    "dayy_giao",
    "rong_giao",
    "dai_giao",
    "sothanh_giao",
    "sokhoi_giao",
    "ghichu_giao",
    "nguyenlieu",
    "nguongoc",
    "chatluong_yc",
    "dayy_yc",
    "rong_yc",
    "dai_yc",
    "sothanh_yc",
    "sokhoi_yc",
    "ghichu_yc"
   ]
  },
  {
   "page": "dq_don_hang_proforma_invoice_add_order_no",
   "title": "Thêm từ đơn hàng khác",
   "dataSource": "ds_order_detail",
   "fromForm": "frmProformaInvoiceAdd_OrderNo",
   "matchType": "title",
   "setFields": [
    "order_number",
    "cust_po_number",
    "range",
    "id",
    "order_qty"
   ]
  },
  {
   "page": "dq_don_hang_dao_dondathang",
   "title": "Tạo đơn đặt hàng dao",
   "dataSource": "ds_dondathang",
   "fromForm": "frm_Dao_dondathang",
   "matchType": "title",
   "setFields": [
    "ghichu",
    "maddh",
    "lan_sua",
    "mancc",
    "tenncc",
    "loaiddh",
    "ngaydat",
    "ngaygiao",
    "donhang",
    "create_by",
    "create_date",
    "trangthai",
    "pheduyet",
    "ngayky",
    "loaithanhtoan",
    "bophan"
   ]
  },
  {
   "page": "dq_don_hang_tong_hop_don_hang",
   "title": "Tổng hợp đơn hàng xuất khẩu",
   "dataSource": "ds_order",
   "fromForm": "frmTongHopDonHang",
   "matchType": "title",
   "setFields": [
    "cust_po_number",
    "order_number",
    "range",
    "fsc_id",
    "ncc_phoi",
    "ncc_dinhhinh",
    "ncc_son",
    "cont_qty",
    "order_date",
    "ship_date",
    "target_date",
    "kehoach_hangtrang",
    "actual_date",
    "danhgia",
    "trangthai_donhang",
    "remark2",
    "id"
   ]
  },
  {
   "page": "dq_don_hang_banhang_add",
   "title": "Bán hàng",
   "dataSource": "ds_sanpham",
   "fromForm": "frm_banhangAdd",
   "matchType": "title",
   "setFields": [
    "masp",
    "tensp",
    "dvt",
    "id",
    "dongia",
    "ghichu"
   ]
  },
  {
   "page": "dq_don_hang_proforma_invoice_add",
   "title": "Thêm Proforma Invoice",
   "dataSource": "ds_sanpham",
   "fromForm": "frmProformaInvoiceAdd",
   "matchType": "title",
   "setFields": [
    "id",
    "masp",
    "masp_khachhang",
    "tensp",
    "cbm",
    "dongia",
    "dvt"
   ]
  },
  {
   "page": "dq_don_hang_list_purchase_order_list",
   "title": "Danh sách đơn đặt hàng",
   "dataSource": "ds_dondathang",
   "fromForm": "frmListPurchaseOrderList",
   "matchType": "title",
   "setFields": [
    "maddh",
    "mancc",
    "tenncc",
    "loaiddh",
    "trangthai"
   ]
  },
  {
   "page": "dq_don_hang_banhanggo_phieudoihang_add",
   "title": "Phiếu đổi hàng",
   "dataSource": "ds_dexuat_phoi_chitiet",
   "fromForm": "frm_banhanggo_PhieudoihangAdd",
   "matchType": "title",
   "setFields": [
    "id",
    "dexuat_id",
    "sothanh_yc",
    "sokhoi_yc"
   ]
  },
  {
   "page": "dq_don_hang_tu_dong_tao_don_hang",
   "title": "Tự động tạo đơn hàng",
   "dataSource": "ds_order_detail",
   "fromForm": "frmTuDongTaoDonHang",
   "matchType": "title",
   "setFields": [
    "price",
    "amount",
    "remark",
    "range"
   ]
  },
  {
   "page": "dq_don_hang_tong_hop_chi_tiet_don_hang2",
   "title": "Tổng hợp chi tiết theo đơn hàng",
   "dataSource": "ds_dinhmuc_govan",
   "fromForm": "frmTongHopChiTietDonHang2",
   "matchType": "title",
   "setFields": [
    "masp",
    "chitiet",
    "nguyenlieu",
    "dayy_tc",
    "rong_tc",
    "dai_tc",
    "soluong_tc",
    "ghichu",
    "veneer_canhngan",
    "veneer_canhdai"
   ]
  },
  {
   "page": "dq_don_hang_banhanggo_danh_sach_de_xuat_phoi3",
   "title": "Danh sách đề xuất phôi",
   "dataSource": "ds_dexuat_phoi_chitiet",
   "fromForm": "frm_banhanggo_DanhSachDeXuatPhoi",
   "matchType": "title",
   "setFields": [
    "dexuat_id",
    "id",
    "isfinish",
    "ngaygiaophoi",
    "nguongoc_giao",
    "chatluong_giao",
    "dayy_giao",
    "rong_giao",
    "dai_giao",
    "sothanh_giao",
    "sokhoi_giao",
    "ghichu_giao",
    "nguyenlieu",
    "nguongoc",
    "chatluong_yc",
    "dayy_yc",
    "rong_yc",
    "dai_yc",
    "sothanh_yc",
    "sokhoi_yc",
    "ghichu_yc"
   ]
  },
  {
   "page": "dq_don_hang_order_number_add3",
   "title": "Tạo đơn hàng",
   "dataSource": "ds_order_detail",
   "fromForm": "frmOrderNumberAdd2",
   "matchType": "title",
   "setFields": [
    "order_qty",
    "price",
    "currency",
    "cbm",
    "id",
    "range",
    "cust_item_number",
    "color",
    "material",
    "test_run_qty"
   ]
  },
  {
   "page": "dq_don_hang_order_number_add2",
   "title": "Tạo đơn hàng",
   "dataSource": "ds_sanpham",
   "fromForm": "frmOrderNumberAdd2",
   "matchType": "title",
   "setFields": [
    "masp",
    "tensp",
    "cbm",
    "id"
   ]
  },
  {
   "page": "dq_don_hang_do_don_hang",
   "title": "Phát hành đơn hàng",
   "dataSource": "ds_sanpham",
   "fromForm": "frmDoDonHang",
   "matchType": "title",
   "setFields": [
    "id",
    "masp",
    "isgovan",
    "isngukim",
    "isbaobi",
    "isson",
    "isveneer",
    "isbvkt",
    "isbvdg",
    "isbvai"
   ]
  },
  {
   "page": "dq_don_hang_order_example_add",
   "title": "Thông tin đơn hàng mẫu",
   "dataSource": "ds_order_detail",
   "fromForm": "frmOrderExampleAdd",
   "matchType": "title",
   "setFields": [
    "order_qty",
    "price",
    "currency",
    "cbm",
    "id",
    "range",
    "cust_item_number",
    "color",
    "material",
    "test_run_qty",
    "remark"
   ]
  },
  {
   "page": "dq_don_hang_order_example",
   "title": "frmOrderExample",
   "dataSource": "ds_order_detail",
   "fromForm": "frmOrderExample",
   "matchType": "title",
   "setFields": [
    "order_number",
    "customer",
    "order_date",
    "ship_date",
    "order_qty",
    "finished",
    "create_by",
    "create_date",
    "id",
    "cbm",
    "remark"
   ]
  },
  {
   "page": "dq_don_hang_danh_sach_don_hang_theo_ngay",
   "title": "Thống kê đơn hàng",
   "dataSource": "ds_order_detail",
   "fromForm": "frmDashboardOrder",
   "matchType": "title",
   "setFields": [
    "customer",
    "order_number",
    "item_number",
    "order_qty",
    "finished"
   ]
  },
  {
   "page": "dq_san_pham_sanpham",
   "title": "Danh sách sản phẩm",
   "dataSource": "ds_sanpham",
   "fromForm": "frmThongtinsanpham",
   "matchType": "title",
   "setFields": [
    "id",
    "masp",
    "tensp",
    "dai",
    "rong",
    "cao",
    "dvt"
   ]
  },
  {
   "page": "dq_don_hang_ke_hoach_hang_trang_don_hang",
   "title": "Kế hoạch đơn hàng trắng",
   "dataSource": "ds_m_op",
   "fromForm": "frmKeHoachHangTrang_DonHang",
   "matchType": "title",
   "setFields": [
    "n_op",
    "id"
   ]
  },
  {
   "page": "dq_san_xuat_ke_hoach_san_xuat_po2_htr_add",
   "title": "Thêm đơn hàng",
   "dataSource": "ds_dondathang",
   "fromForm": "frmKeHoachSanXuatPO2_HTR_Add",
   "matchType": "title",
   "setFields": [
    "maddh",
    "tenncc",
    "trangthai",
    "loaiddh",
    "donhang"
   ]
  },
  {
   "page": "dq_san_xuat_quytrinh_sanxuat_copy",
   "title": "Sao chép quy trình sản xuất",
   "dataSource": "ds_dinhmuc_govan",
   "fromForm": "frm_quytrinh_sanxuat_copy",
   "matchType": "title",
   "setFields": [
    "masp",
    "mact",
    "chitiet"
   ]
  },
  {
   "page": "dq_san_xuat_ke_hoach_san_xuat_po",
   "title": "Kế hoạch sản xuất",
   "dataSource": "ds_order",
   "fromForm": "frmKeHoachSanXuatPO",
   "matchType": "title",
   "setFields": [
    "order_number",
    "range",
    "cont_qty",
    "customer",
    "vendor_id",
    "id"
   ]
  },
  {
   "page": "dq_san_xuat_quy_trinh_san_xuat",
   "title": "Quy trình sản xuất",
   "dataSource": "ds_order_detail",
   "fromForm": "frm_QuyTrinh_SanXuat",
   "matchType": "title",
   "setFields": [
    "order_number",
    "item_number",
    "description",
    "order_qty"
   ]
  },
  {
   "page": "dq_san_xuat_quytrinh_sanxuat_import",
   "title": "Nạp quy trình sản xuất",
   "dataSource": "ds_dinhmuc_govan",
   "fromForm": "frm_quytrinh_sanxuat_import",
   "matchType": "title",
   "setFields": [
    "masp",
    "mact",
    "nguyenlieu",
    "stt"
   ]
  },
  {
   "page": "dq_san_xuat_tien_do_chuyen_son_add",
   "title": "Nhập tiến độ chuyền sơn",
   "dataSource": "ds_dinhmuc_govan",
   "fromForm": "frmTienDoChuyenSonAdd",
   "matchType": "title",
   "setFields": [
    "masp",
    "stt",
    "mact",
    "chitiet",
    "nguyenlieu",
    "dayy_tc",
    "rong_tc",
    "dai_tc",
    "soluong_tc"
   ]
  },
  {
   "page": "dq_san_xuat_muc_tieu_san_xuat2",
   "title": "Mục tiêu sản xuất",
   "dataSource": "ds_muctieu_sanxuat2",
   "fromForm": "frmMucTieuSanXuat2",
   "matchType": "title",
   "setFields": [
    "mabophan",
    "songuoi",
    "songay",
    "mucthuong",
    "phantram_tang",
    "col1",
    "col2",
    "col3",
    "col4",
    "col5",
    "col6",
    "col7",
    "col8",
    "col9",
    "col10",
    "col11",
    "col12",
    "col13",
    "col14",
    "col15",
    "col16",
    "col17",
    "col18",
    "col22",
    "col23",
    "col19",
    "col20",
    "col21",
    "nam",
    "thang",
    "id"
   ]
  },
  {
   "page": "dq_san_pham_thong_tin_san_pham2_add",
   "title": "Thêm thông tin sản phẩm",
   "dataSource": "ds_sanpham",
   "fromForm": "frmThongTinSanPham2Add",
   "matchType": "title",
   "setFields": [
    "hinhanh",
    "id",
    "masp",
    "tensp",
    "ketcau",
    "nguyenlieu",
    "ghichu",
    "tieuchuan",
    "mausac"
   ]
  },
  {
   "page": "dq_san_xuat_tien_do_hang_trang3",
   "title": "Nhập tiến độ sản xuất",
   "dataSource": "ds_pallet",
   "fromForm": "frmTienDoHangTrang3",
   "matchType": "title",
   "setFields": [
    "mahtr",
    "stt",
    "tenct",
    "nguyenlieu",
    "dayy_tc",
    "rong_tc",
    "dai_tc",
    "soluong_can",
    "mact"
   ]
  },
  {
   "page": "dq_san_xuat_ke_hoach_hang_trang_sap_xep",
   "title": "Sắp xếp đơn hàng",
   "dataSource": "ds_pallet",
   "fromForm": "frmKeHoachHangTrang_SapXep",
   "matchType": "title",
   "setFields": [
    "donhang",
    "stt"
   ]
  },
  {
   "page": "dq_san_xuat_quytrinh_sanxuat_reprint",
   "title": "frm_quytrinh_sanxuat_reprint",
   "dataSource": "ds_sanpham",
   "fromForm": "frm_quytrinh_sanxuat_reprint",
   "matchType": "title",
   "setFields": [
    "nguyenlieu",
    "id"
   ]
  },
  {
   "page": "dq_san_pham_quy_trinh_san_pham_copy",
   "title": "Copy quy trình sản phẩm",
   "dataSource": "ds_sanpham",
   "fromForm": "frmQuyTrinhSanPhamCopy",
   "matchType": "title",
   "setFields": [
    "masp",
    "tensp",
    "id",
    "hehang",
    "loaisp",
    "nguyenlieu",
    "ghichu"
   ]
  },
  {
   "page": "dq_san_pham_quy_trinh_san_pham",
   "title": "Quy trình sản phẩm",
   "dataSource": "ds_sanpham",
   "fromForm": "frmQuyTrinhSanPham2",
   "matchType": "title",
   "setFields": [
    "hehang",
    "masp",
    "tensp",
    "id",
    "loaisp",
    "nguyenlieu"
   ]
  },
  {
   "page": "dq_san_pham_sanpham_multiselect",
   "title": "Ẩn nhiều sản phẩm",
   "dataSource": "ds_sanpham",
   "fromForm": "frm_sanpham_multiselect",
   "matchType": "title",
   "setFields": [
    "hehang",
    "masp",
    "tensp",
    "customer"
   ]
  },
  {
   "page": "dq_san_pham_san_pham_mau_nhap_xuat",
   "title": "Nhập - Xuất hàng mẫu",
   "dataSource": "ds_phieubaogia",
   "fromForm": "frmSanPhamMau_NhapXuat",
   "matchType": "title",
   "setFields": [
    "sophieu",
    "ghichu",
    "nguoitao",
    "ngaytao",
    "nguoisua",
    "ngaysua",
    "id"
   ]
  },
  {
   "page": "dq_san_pham_tao_phieu_san_pham",
   "title": "Tạo phiếu sản phẩm",
   "dataSource": "ds_pallet",
   "fromForm": "frmTaoPhieuSanPham",
   "matchType": "title",
   "setFields": [
    "stt",
    "tenct",
    "nguyenlieu",
    "dayy_tc",
    "rong_tc",
    "dai_tc",
    "soluong_tc",
    "soluong_donhang",
    "soluong_can",
    "card_qty",
    "id",
    "donhang",
    "masp",
    "iscreatecard"
   ]
  },
  {
   "page": "dq_san_pham_quy_trinh_san_pham2",
   "title": "Quy trình sản phẩm",
   "dataSource": "ds_sanpham",
   "fromForm": "frmQuyTrinhSanPham2",
   "matchType": "title",
   "setFields": [
    "hehang",
    "masp",
    "tensp",
    "id",
    "loaisp",
    "nguyenlieu"
   ]
  },
  {
   "page": "dq_san_pham_khoi_luong_san_pham",
   "title": "Trọng lượng sản phẩm",
   "dataSource": "ds_sanpham",
   "fromForm": "frmKhoiLuongSanPham",
   "matchType": "title",
   "setFields": [
    "masp",
    "tensp",
    "nguyenlieu",
    "m3_tc"
   ]
  },
  {
   "page": "dq_bao_cao_bao_cao_final_add",
   "title": "Nhập Báo cáo Kiểm tra",
   "dataSource": "ds_baocao_final_muckiemtra",
   "fromForm": "frmBaoCaoFinalAdd",
   "matchType": "title",
   "setFields": [
    "masp",
    "tensp",
    "diengiai",
    "soluong_kiemtra",
    "danhgia",
    "hanhdong",
    "ghichu",
    "item_id"
   ]
  },
  {
   "page": "dq_bao_cao_thong_bao",
   "title": "Thông báo",
   "dataSource": "ds_sanpham",
   "fromForm": "frmThongBao",
   "matchType": "title",
   "setFields": [
    "masp",
    "tensp",
    "ngaybaogia",
    "hanbaogia"
   ]
  },
  {
   "page": "dq_bao_gia_baogia_sanpham_auto",
   "title": "Báo giá tự động",
   "dataSource": "ds_sanpham",
   "fromForm": "frm_baogia_sanpham_auto",
   "matchType": "title",
   "setFields": [
    "masp",
    "tensp",
    "nguyenlieu",
    "m3",
    "ghichu",
    "id",
    "quycach",
    "mausac",
    "dvt",
    "dongia",
    "loaitien"
   ]
  },
  {
   "page": "dq_bao_gia_baogia_sanpham_ver3",
   "title": "Báo giá sản phẩm",
   "dataSource": "ds_sanpham",
   "fromForm": "frmBaoGia3",
   "matchType": "title",
   "setFields": [
    "masp_nhamay",
    "tensp",
    "hehang",
    "nguyenlieu",
    "m3_tc",
    "masp",
    "id",
    "quycach",
    "mausac",
    "dongia",
    "loaitien"
   ]
  },
  {
   "page": "dq_bao_gia_baogia_sanpham_ver4",
   "title": "Báo giá sản phẩm",
   "dataSource": "ds_sanpham",
   "fromForm": "frmBaoGia3",
   "matchType": "title",
   "setFields": [
    "masp_nhamay",
    "tensp",
    "hehang",
    "nguyenlieu",
    "m3_tc",
    "masp",
    "id",
    "quycach",
    "mausac",
    "dongia",
    "loaitien"
   ]
  },
  {
   "page": "dq_bao_cao_theo_doi_dat_hang",
   "title": "Theo dõi đơn đặt hàng",
   "dataSource": "ds_order",
   "fromForm": "frm_theodoi_dondathang",
   "matchType": "title",
   "setFields": [
    "vendor_id",
    "create_by",
    "id"
   ]
  },
  {
   "page": "dq_bao_gia_bao_gia_vat_tu_go_van",
   "title": "Báo giá vật tư gỗ ván",
   "dataSource": "ds_tonkho_sum_material",
   "fromForm": "frmBaoGiaVatTuGoVan",
   "matchType": "title",
   "setFields": [
    "ghichu",
    "nhom",
    "mavt",
    "mota",
    "dayy",
    "rong",
    "dai",
    "dvt",
    "soluong",
    "quycach",
    "dongia"
   ]
  },
  {
   "page": "dq_bao_gia_baogia_danhsach",
   "title": "Danh sách báo giá",
   "dataSource": "ds_sanpham",
   "fromForm": "frmDanhSachBaoGia3_2",
   "matchType": "title",
   "setFields": [
    "masp",
    "mausac",
    "heso_mam",
    "dongia_mam",
    "tensp",
    "hehang"
   ]
  },
  {
   "page": "dq_bao_cao_bao_cao_nguyen_phu_lieu_add",
   "title": "Nguyên phụ liệu",
   "dataSource": "ds_dondathang",
   "fromForm": "frmBaoCaoNguyenPhuLieuAdd",
   "matchType": "title",
   "setFields": [
    "id",
    "donhang",
    "ghichu"
   ]
  },
  {
   "page": "dq_bao_cao_thong_tin_nguoi_phu_trach_ky_thuat_add2",
   "title": "Cập nhật thông tin người phụ trách",
   "dataSource": "ds_sanpham",
   "fromForm": "frm_ThongTinNguoiPhuTrach_KyThuat_Add2",
   "matchType": "title",
   "setFields": [
    "id",
    "masp",
    "hehang",
    "tensp"
   ]
  },
  {
   "page": "dq_bao_cao_bao_cao_hoan_thien_add",
   "title": "Báo cáo hàng ngày",
   "dataSource": "ds_baocao_hangloi",
   "fromForm": "frmBaoCaoHoanThienAdd",
   "matchType": "title",
   "setFields": [
    "id",
    "donhang",
    "masp",
    "mact",
    "tenct",
    "dayy",
    "rong",
    "dai",
    "soluong",
    "ghichu"
   ]
  },
  {
   "page": "dq_bao_cao_bao_cao_hien_dien",
   "title": "Báo cáo hiện diện",
   "dataSource": "ds_m_op",
   "fromForm": "frmBaoCaoHienDien",
   "matchType": "title",
   "setFields": [
    "c_op",
    "n_op",
    "id"
   ]
  },
  {
   "page": "dq_bao_gia_baogia_sanpham_info",
   "title": "Thông tin chi tiết báo giá sản phẩm",
   "dataSource": "ds_baogia_donggoi",
   "fromForm": "frm_baogia_sanpham_info",
   "matchType": "title",
   "setFields": [
    "stt",
    "chitiet",
    "ghichu",
    "masp",
    "mact",
    "quycach",
    "dvt",
    "soluong",
    "dongia"
   ]
  },
  {
   "page": "dq_bao_cao_thong_ke_so_luong_add",
   "title": "Thống kê số lượng",
   "dataSource": "ds_sanpham",
   "fromForm": "frmThongKeSoLuong",
   "matchType": "title",
   "setFields": [
    "masp",
    "tensp",
    "nguyenlieu"
   ]
  },
  {
   "page": "dq_bao_cao_bao_cao_hang_loi",
   "title": "Báo cáo sản phẩm không phù hợp",
   "dataSource": "ds_dinhmuc_govan",
   "fromForm": "frmBaoCaoHangLoi",
   "matchType": "title",
   "setFields": [
    "chitiet",
    "mact",
    "stt",
    "nguyenlieu"
   ]
  },
  {
   "page": "dq_bao_cao_bao_cao_rot_chuyen_add",
   "title": "Báo cáo rớt chuyền",
   "dataSource": "ds_sanpham",
   "fromForm": "frmBaoCaoRotChuyenAdd",
   "matchType": "title",
   "setFields": [
    "masp",
    "tensp",
    "id"
   ]
  },
  {
   "page": "dq_bao_cao_bao_cao_kiem_tra_chat_luong",
   "title": "Báo cáo kiểm tra chất lượng",
   "dataSource": "ds_thaydoi_kythuat",
   "fromForm": "frmBaoCaoKiemTraChatLuong2",
   "matchType": "title",
   "setFields": [
    "masp",
    "tenct",
    "mact"
   ]
  },
  {
   "page": "dq_ke_toan_danh_sach_quy_trinh",
   "title": "Danh sách quy trình đã phát hành",
   "dataSource": "ds_sanpham",
   "fromForm": "frmDanhSachQuyTrinh",
   "matchType": "title",
   "setFields": [
    "hehang",
    "masp",
    "tensp",
    "customer",
    "nguyenlieu"
   ]
  },
  {
   "page": "dq_bao_gia_bao_gia_phoi",
   "title": "Báo giá phôi",
   "dataSource": "ds_sanpham",
   "fromForm": "frmBaoGiaPhoi",
   "matchType": "title",
   "setFields": [
    "nguyenlieu",
    "id",
    "m3_tc",
    "ghichu",
    "masp",
    "tensp",
    "hehang",
    "customer"
   ]
  },
  {
   "page": "dq_bao_gia_baogia_sanpham_ver2",
   "title": "Báo giá sản phẩm",
   "dataSource": "ds_sanpham",
   "fromForm": "frmBaoGia3",
   "matchType": "title",
   "setFields": [
    "masp_nhamay",
    "tensp",
    "hehang",
    "nguyenlieu",
    "m3_tc",
    "masp",
    "id",
    "quycach",
    "mausac",
    "dongia",
    "loaitien"
   ]
  },
  {
   "page": "dq_ke_toan_denghi_thanhtoan_tonghop",
   "title": "frm_denghi_thanhtoan_tonghop",
   "dataSource": "de_nghi_thanh_toan_joined_019eb9",
   "fromForm": "frm_denghi_thanhtoan_tonghop",
   "matchType": "title",
   "setFields": [
    "ngaycan_thanhtoan",
    "loaithanhtoan",
    "thanhtien",
    "hinhthuc_thanhtoan",
    "loaitien"
   ]
  },
  {
   "page": "dq_ke_toan_danh_sach_quy_trinh2",
   "title": "Quy trình sản phẩm (theo mã nhà máy)",
   "dataSource": "ds_sanpham",
   "fromForm": "frmDanhSachQuyTrinh2",
   "matchType": "title",
   "setFields": [
    "hehang",
    "masp_nhamay",
    "tensp",
    "masp",
    "nguyenlieu"
   ]
  },
  {
   "page": "dq_bang_mau_banve_upload_ban_ve2",
   "title": "Tải bản vẽ",
   "dataSource": "ds_banve",
   "fromForm": "frmUploadBanVe2",
   "matchType": "title",
   "setFields": [
    "id",
    "phanloai",
    "masp",
    "tensp",
    "hehang"
   ]
  },
  {
   "page": "dq_khach_hang_ncc_khach_hang_info",
   "title": "Thông tin khách hàng",
   "dataSource": "ds_order_detail",
   "fromForm": "frmKhachHangInfo",
   "matchType": "title",
   "setFields": [
    "order_qty",
    "amount",
    "order_number",
    "cust_po_number",
    "order_date",
    "ship_date",
    "range",
    "remark",
    "payment_term"
   ]
  },
  {
   "page": "dq_de_xuat_de_xuat_phoi_add5",
   "title": "Đề xuất phôi",
   "dataSource": "ds_dexuat_phoi_chitiet",
   "fromForm": "frmDeXuatPhoiAdd",
   "matchType": "title",
   "setFields": [
    "id",
    "dexuat_id",
    "nguyenlieu",
    "nguongoc"
   ]
  },
  {
   "page": "dq_de_xuat_chi_tiet_de_xuat_phoi",
   "title": "Đề xuất phôi",
   "dataSource": "ds_dexuat_phoi_chitiet",
   "fromForm": "frmDeXuatPhoiAdd",
   "matchType": "title",
   "setFields": [
    "id",
    "dexuat_id",
    "nguyenlieu",
    "nguongoc"
   ]
  },
  {
   "page": "dq_de_xuat_de_xuat_phoi_add4",
   "title": "Đề xuất phôi",
   "dataSource": "ds_dexuat_phoi_chitiet",
   "fromForm": "frmDeXuatPhoiAdd",
   "matchType": "title",
   "setFields": [
    "id",
    "dexuat_id",
    "nguyenlieu",
    "nguongoc"
   ]
  },
  {
   "page": "dq_bang_mau_banve_danh_sach_ban_ve2",
   "title": "Danh sách bản vẽ đã phát hành",
   "dataSource": "ds_banve",
   "fromForm": "frmDanhSachBanVe2",
   "matchType": "title",
   "setFields": [
    "id",
    "masp",
    "tensp",
    "khachhang",
    "hehang",
    "filepath",
    "seq1",
    "seq2",
    "phanloai",
    "create_by",
    "create_date",
    "update_by",
    "update_date",
    "active"
   ]
  },
  {
   "page": "dq_de_xuat_chi_tiet_de_xuat_mua_hang",
   "title": "Đề xuất mua hàng",
   "dataSource": "ds_phieuyeucau",
   "fromForm": "frmDeXuatMuahang",
   "matchType": "title",
   "setFields": [
    "id",
    "bophan",
    "loaidexuat",
    "nguoiduyet",
    "nguoiky",
    "ngaytao",
    "active"
   ]
  },
  {
   "page": "dq_bang_mau_banve_banve",
   "title": "Chi tiết bản vẽ",
   "dataSource": "ds_banve",
   "fromForm": "frm_banve",
   "matchType": "title",
   "setFields": [
    "hehang",
    "masp",
    "tensp",
    "create_date",
    "update_date"
   ]
  },
  {
   "page": "dq_bang_mau_banve_banve_view3",
   "title": "frm_banve_view3",
   "dataSource": "ds_dinhmuc_govan",
   "fromForm": "frm_banve_view3",
   "matchType": "title",
   "setFields": [
    "masp",
    "id",
    "stt",
    "mact",
    "chitiet",
    "nguyenlieu",
    "dayy_tc",
    "rong_tc",
    "dai_tc",
    "soluong_tc",
    "m3_tc",
    "ghichu"
   ]
  },
  {
   "page": "dq_bang_mau_banve_banve2",
   "title": "Danh sách bản vẽ",
   "dataSource": "ds_banve",
   "fromForm": "frmDanhSachBanVe",
   "matchType": "title",
   "setFields": [
    "id",
    "hehang",
    "masp",
    "phanloai",
    "tensp"
   ]
  },
  {
   "page": "dq_pallet_danh_sach_pallet",
   "title": "Danh sách phiếu pallet",
   "dataSource": "ds_pallet_card",
   "fromForm": "frmDanhSachPallet",
   "matchType": "title",
   "setFields": [
    "soluong",
    "card_no",
    "stt_snap",
    "mact_snap",
    "tenct_snap",
    "nguyenlieu_snap",
    "dayy_tc_snap",
    "rong_tc_snap",
    "dai_tc_snap",
    "reissue_qty",
    "issue_date",
    "card_seq"
   ]
  },
  {
   "page": "frm_banve_test_5f0012",
   "title": "frm_banve_test",
   "dataSource": "ds_dinhmuc_govan",
   "fromForm": "frm_banve_test",
   "matchType": "title",
   "setFields": [
    "stt",
    "mact",
    "chitiet",
    "nguyenlieu",
    "dayy_tc",
    "rong_tc",
    "dai_tc",
    "soluong_tc",
    "m3_tc",
    "ghichu",
    "masp"
   ]
  },
  {
   "page": "dq_bang_mau_banve_danh_sach_ban_ve",
   "title": "Danh sách bản vẽ",
   "dataSource": "ds_banve",
   "fromForm": "frmDanhSachBanVe",
   "matchType": "title",
   "setFields": [
    "id",
    "hehang",
    "masp",
    "phanloai",
    "tensp"
   ]
  },
  {
   "page": "dq_pallet_in_pallet_2",
   "title": "In Phiếu Pallet",
   "dataSource": "ds_dinhmuc_govan",
   "fromForm": "frm_quytrinh_sanxuat_danhsach2",
   "matchType": "title",
   "setFields": [
    "chitiet",
    "masp",
    "stt",
    "mact",
    "nguyenlieu",
    "id",
    "dayy_tc",
    "rong_tc",
    "dai_tc",
    "soluong_tc",
    "m3_tc",
    "ghichu"
   ]
  },
  {
   "page": "frm_kiemtra_dinhmuc_bbf4eb",
   "title": "frm_kiemtra_dinhmuc",
   "dataSource": "ds_dinhmuc_govan",
   "fromForm": "frm_kiemtra_dinhmuc",
   "matchType": "title",
   "setFields": [
    "mact",
    "stt",
    "chitiet",
    "nguyenlieu",
    "dayy_tc",
    "rong_tc",
    "dai_tc",
    "soluong_tc",
    "m3_tc",
    "dayy_sc",
    "rong_sc",
    "dai_sc",
    "m3_sc",
    "ghichu",
    "masp"
   ]
  },
  {
   "page": "dq_ke_toan_denghi_thanhtoan_ncc_add",
   "title": "Thông tin người cần thanh toán",
   "dataSource": "de_nghi_thanh_toan_joined_019eb9",
   "fromForm": "frmPhieuDeNghiThanhToan",
   "matchType": "fallback",
   "setFields": [
    "id",
    "ngayphieu",
    "sophieu",
    "nguoidenghi",
    "bophan",
    "nguoitao",
    "ngaytao",
    "loaithanhtoan",
    "noidung",
    "dathanhtoan",
    "sotien",
    "thue",
    "phigiaohang",
    "thanhtien",
    "loaitien",
    "tygia",
    "nguoiduyet",
    "ngayduyet"
   ]
  }
 ]
}